griffe_endstone/__init__.py
griffe_endstone/extension.py
griffe_endstone-0.1.1.dist-info/METADATA
griffe_endstone-0.1.1.dist-info/WHEEL
griffe_endstone-0.1.1.dist-info/licenses/LICENSE
griffe_endstone-0.1.1.dist-info/RECORD
