Metadata-Version: 2.3
Name: griffe-endstone
Version: 0.1.1
Summary: Griffe extension for the Endstone project.
Author-email: Vincent <magicdroidx@gmail.com>
License: MIT License
License-File: LICENSE
Keywords: endstone,griffe-extension,mkdocstrings
Requires-Dist: griffe
